{
  "10158809": {
    "status": "valid"
  },
  "10178589": {
    "status": "valid"
  },
  "10693563": {
    "status": "valid"
  },
  "10710953": {
    "status": "valid"
  },
  "10796456": {
    "status": "valid"
  },
  "11162583": {
    "status": "valid"
  },
  "11162722": {
    "status": "valid"
  },
  "11215907": {
    "status": "valid"
  },
  "08189416": {
    "status": "valid"
  },
  "09467212": {
    "status": "valid"
  },
  "06485680": {
    "status": "valid"
  },
  "06389505": {
    "status": "valid"
  },
  "04061490": {
    "status": "valid"
  },
  "06959771": {
    "status": "valid"
  },
  "03281609": {
    "status": "valid"
  },
  "00071430": {
    "status": "valid"
  },
  "06709860": {
    "status": "valid"
  },
  "06755395": {
    "status": "valid"
  },
  "07412959": {
    "status": "valid"
  },
  "08500792": {
    "status": "valid"
  },
  "02833215": {
    "status": "valid"
  },
  "06208660": {
    "status": "valid"
  },
  "05343735": {
    "status": "valid"
  },
  "08028170": {
    "status": "valid"
  },
  "07166287": {
    "status": "valid"
  },
  "00450577": {
    "status": "valid"
  },
  "01615250": {
    "status": "valid"
  },
  "07470046": {
    "status": "valid"
  },
  "07272688": {
    "status": "valid"
  },
  "01852806": {
    "status": "valid"
  },
  "08268173": {
    "status": "valid"
  },
  "04042697": {
    "status": "valid"
  },
  "00858856": {
    "status": "valid"
  },
  "08146349": {
    "status": "valid"
  },
  "08148663": {
    "status": "valid"
  },
  "02953188": {
    "status": "valid"
  },
  "03635234": {
    "status": "valid"
  },
  "04283187": {
    "status": "valid"
  },
  "04129612": {
    "status": "valid"
  },
  "01645789": {
    "status": "valid"
  },
  "01019172": {
    "status": "valid"
  },
  "03553908": {
    "status": "valid"
  },
  "05359946": {
    "status": "valid"
  },
  "07560790": {
    "status": "valid"
  },
  "07875755": {
    "status": "valid"
  },
  "07125852": {
    "status": "valid"
  },
  "03512239": {
    "status": "valid"
  },
  "09098450": {
    "status": "valid"
  },
  "02119023": {
    "status": "valid"
  },
  "01526397": {
    "status": "valid"
  },
  "03847630": {
    "status": "valid"
  },
  "00745399": {
    "status": "valid"
  },
  "04807595": {
    "status": "valid"
  },
  "02158849": {
    "status": "valid"
  },
  "06711051": {
    "status": "valid"
  },
  "03183733": {
    "status": "valid"
  },
  "04080619": {
    "status": "valid"
  },
  "00496634": {
    "status": "valid"
  },
  "03250801": {
    "status": "valid"
  },
  "03004311": {
    "status": "valid"
  },
  "04805444": {
    "status": "valid"
  },
  "07640224": {
    "status": "valid"
  },
  "02861426": {
    "status": "valid"
  },
  "05493388": {
    "status": "valid"
  },
  "04454027": {
    "status": "valid"
  },
  "03723803": {
    "status": "valid"
  },
  "06721124": {
    "status": "valid"
  },
  "03807755": {
    "status": "valid"
  },
  "02351132": {
    "status": "valid"
  },
  "07882611": {
    "status": "valid"
  },
  "07882873": {
    "status": "valid"
  },
  "03509985": {
    "status": "valid"
  },
  "04635666": {
    "status": "valid"
  },
  "09362054": {
    "status": "valid"
  },
  "02875213": {
    "status": "valid"
  },
  "00292814": {
    "status": "valid"
  },
  "06718612": {
    "status": "valid"
  },
  "07443722": {
    "status": "valid"
  },
  "02532117": {
    "status": "valid"
  },
  "08053383": {
    "status": "valid"
  },
  "01074935": {
    "status": "valid"
  },
  "06540166": {
    "status": "valid"
  },
  "05914272": {
    "status": "valid"
  },
  "01421128": {
    "status": "valid"
  },
  "04495928": {
    "status": "valid"
  },
  "07248789": {
    "status": "valid"
  },
  "09898578": {
    "status": "valid"
  },
  "04204445": {
    "status": "valid"
  },
  "03935293": {
    "status": "valid"
  },
  "02262602": {
    "status": "valid"
  },
  "00418594": {
    "status": "valid"
  },
  "04137790": {
    "status": "valid"
  },
  "05688323": {
    "status": "valid"
  }
}